splicekit/__init__.py
splicekit/folders.setup
splicekit/splicekit.config.template
splicekit/version
splicekit/clusterlogfc/__init__.py
splicekit/config/__init__.py
splicekit/core/__init__.py
splicekit/core/anchors.py
splicekit/core/annotation.py
splicekit/core/comps_edgeR.R
splicekit/core/delta_dar.py
splicekit/core/exons.py
splicekit/core/features.py
splicekit/core/genes.py
splicekit/core/jbrowse2.py
splicekit/core/juan.py
splicekit/core/junctions.py
splicekit/core/motifs.py
splicekit/core/patterns.py
splicekit/core/promisc.py
splicekit/core/report.py
splicekit/judge/__init__.py
splicekit/june/__init__.py
splicekit/report/__init__.py
splicekit-0.8.dist-info/licenses/LICENSE
splicekit-0.8.dist-info/METADATA
splicekit-0.8.dist-info/WHEEL
splicekit-0.8.dist-info/entry_points.txt
splicekit-0.8.dist-info/top_level.txt
splicekit-0.8.dist-info/RECORD
