Metadata-Version: 2.4
Name: splicekit
Version: 0.8
Summary: splicekit: comprehensive toolkit for splicing analysis from short-read RNA-seq
Home-page: https://github.com/bedapub/splicekit
Author: Roche, PMDA Spliceosome team
Author-email: gregor.rot@gmail.com
Keywords: splicekit,splicing,transcriptomics,bioinformatics
Classifier: Programming Language :: Python :: 3
License-File: LICENSE
Requires-Dist: levenshtein
Requires-Dist: logomaker
Requires-Dist: plotly
Requires-Dist: python-dateutil>=2.8.2
Requires-Dist: pybio
Requires-Dist: scanRBP
Requires-Dist: pysam
Requires-Dist: numpy>=1.20
Requires-Dist: psutil
Requires-Dist: bs4
Requires-Dist: requests
Requires-Dist: rangehttpserver
Dynamic: author
Dynamic: author-email
Dynamic: classifier
Dynamic: description
Dynamic: description-content-type
Dynamic: home-page
Dynamic: keywords
Dynamic: license-file
Dynamic: requires-dist
Dynamic: summary
